midas_dlp/__init__.py
midas_dlp/model.py
midas_dlp/module.py
midas_dlpdata-2.0.0.dist-info/LICENSE
midas_dlpdata-2.0.0.dist-info/METADATA
midas_dlpdata-2.0.0.dist-info/WHEEL
midas_dlpdata-2.0.0.dist-info/top_level.txt
midas_dlpdata-2.0.0.dist-info/RECORD
