Metadata-Version: 2.1
Name: midas-dlpdata
Version: 2.0.0
Summary: A Midas module for commercial buildings datasets.
Author-email: Stephan Balduin <stephan.balduin@offis.de>
Project-URL: Documentation, https://midas-mosaik.gitlab.io/midas
Requires-Python: >=3.8
License-File: LICENSE
Requires-Dist: midas-powerseries~=2.0.0rc2
Requires-Dist: wget
Requires-Dist: xlrd
